settings/__init__.py
settings_read_write-1.3.dist-info/METADATA
settings_read_write-1.3.dist-info/WHEEL
settings_read_write-1.3.dist-info/top_level.txt
settings_read_write-1.3.dist-info/zip-safe
settings_read_write-1.3.dist-info/RECORD
