Metadata-Version: 2.1
Name: settings-read-write
Version: 1.3
Summary: Manage (read/ write) settings file in different formats (eg. JAML, JSON, ...)
Home-page: https://github.com/CastellaniDavide/settings
Author: CastellaniDavide
Author-email: help@castellanidavide.it
License: GNU
Platform: linux_distibution
Requires-Python: >=3.7
Requires-Dist: PyYAML
